CONTRIBUTING.md
MANIFEST.in
README.rst
setup.py
chrome_webstore_download/__init__.py
chrome_webstore_download/download.py
chrome_webstore_download.egg-info/PKG-INFO
chrome_webstore_download.egg-info/SOURCES.txt
chrome_webstore_download.egg-info/dependency_links.txt
chrome_webstore_download.egg-info/entry_points.txt
chrome_webstore_download.egg-info/requires.txt
chrome_webstore_download.egg-info/top_level.txt