Metadata-Version: 1.2
Name: chrome-webstore-download
Version: 0.1.3
Summary: Google Chrome Webstore downloader
Home-page: http://github.com/jaymoulin/docker-google-chrome-webstore-download/
Author: Jay MOULIN
Author-email: jaymoulin@gmail.com
License: MIT
Platform: UNKNOWN
Classifier: Development Status :: 5 - Production/Stable
Classifier: Programming Language :: Python
Classifier: License :: OSI Approved :: MIT License
Classifier: Natural Language :: English
Classifier: Operating System :: OS Independent
Classifier: Programming Language :: Python :: 3
Classifier: Topic :: Software Development
Classifier: Intended Audience :: Developers
Requires-Python: >=3
